visplotlib/__init__.py
visplotlib/dims.py
visplotlib/plotly.py
visplotlib/pyplot.py
visplotlib/seaborn.py
visplotlib/visium.mplstyle
visplotlib-0.5.0.dist-info/licenses/LICENSE
visplotlib-0.5.0.dist-info/METADATA
visplotlib-0.5.0.dist-info/WHEEL
visplotlib-0.5.0.dist-info/top_level.txt
visplotlib-0.5.0.dist-info/RECORD
