Metadata-Version: 2.4
Name: visplotlib
Version: 0.5.0
Summary: Extensions to Matplotlib and Seaborn plotting for Visium SA.
Author-email: "Arnaud Dhaene (Visium SA)" <arnaud.dhaene@visium.ch>
Project-URL: Repository, https://github.com/VisiumCH/visplotlib
Classifier: Programming Language :: Python :: 3
Classifier: License :: OSI Approved :: MIT License
Classifier: Operating System :: OS Independent
License-File: LICENSE
Requires-Dist: matplotlib
Requires-Dist: seaborn
Requires-Dist: plotly
Dynamic: license-file
